{
    "code": 0,
    "message": null,
    "data": {
        "pageData": [{
                "id":11111,
                "imgUrl":"www.baidu.com/img/baidu_jgylogo3.gif",
                "imgLink":"www.baidu.com",
                "titleDesc": "标题",
                "sortOrder":"1",
                "isHidden":"0",
                "isDelete": "0",
                "createTime":"2017-5-10",
                "creator":"admin"
            },{
                "id":2222,
                "imgUrl":"www.baidu.com/img/baidu_jgylogo3.gif",
                "imgLink":"www.baidu.com",
                "titleDesc": "标题1",
                "sortOrder":"2",
                "isHidden":"0",
                "isDelete": "0",
                "createTime":"2017-5-11",
                "creator":"admin"
            },{
                "id":3333,
                "imgUrl":"www.baidu.com/img/baidu_jgylogo3.gif",
                "imgLink":"www.baidu.com",
                "titleDesc": "标题2",
                "sortOrder":"3",
                "isHidden":"0",
                "isDelete": "0",
                "createTime":"2017-5-12",
                "creator":"admin"
            },{
                "id":44444,
                "imgUrl":"www.baidu.com/img/baidu_jgylogo3.gif",
                "imgLink":"www.baidu.com",
                "titleDesc": "标题3",
                "sortOrder":"4",
                "isHidden":"0",
                "isDelete": "0",
                "createTime":"2017-5-13",
                "creator":"admin"
            },{
                "id":55555,
                "imgUrl":"www.baidu.com/img/baidu_jgylogo3.gif",
                "imgLink":"www.baidu.com",
                "titleDesc": "标题4",
                "sortOrder":"4",
                "isHidden":"0",
                "isDelete": "0",
                "createTime":"2017-5-15",
                "creator":"admin"
            },{
                "id":66666,
                "imgUrl":"www.baidu.com/img/baidu_jgylogo3.gif",
                "imgLink":"www.baidu.com",
                "titleDesc": "标题5",
                "sortOrder":"5",
                "isHidden":"0",
                "isDelete": "0",
                "createTime":"2017-5-16",
                "creator":"admin"
            }]
    }
}
